python_tivo/__init__.py
python_tivo/connection.py
python_tivo/const.py
python_tivo/response.py
python_tivo-0.0.1.dist-info/DESCRIPTION.rst
python_tivo-0.0.1.dist-info/METADATA
python_tivo-0.0.1.dist-info/RECORD
python_tivo-0.0.1.dist-info/WHEEL
python_tivo-0.0.1.dist-info/metadata.json
python_tivo-0.0.1.dist-info/top_level.txt
