Metadata-Version: 2.0
Name: python-tivo
Version: 0.0.1
Summary: Python module for controlling a TiVo DVR
Home-page: https://github.com/mattjgalloway/python-tivo
Author: mattjgalloway
Author-email: matt@galloway.me.uk
License: MIT
Keywords: tivo
Platform: UNKNOWN
